learning_utils/DataTrackers.py
learning_utils/Memories.py
learning_utils/__init__.py
learning_utils-0.1.1.dist-info/METADATA
learning_utils-0.1.1.dist-info/WHEEL
learning_utils-0.1.1.dist-info/RECORD
